middleware2mysql_pkg/__init__.py
middleware2mysql_pkg/kafka2mysql.py
middleware2mysql_pkg/kafka2mysql_models.py
middleware2mysql_pkg/redis2mysql.py
middleware2mysql_pkg/redis2mysql_models.py
middleware2mysql-0.0.5.dist-info/METADATA
middleware2mysql-0.0.5.dist-info/WHEEL
middleware2mysql-0.0.5.dist-info/top_level.txt
middleware2mysql-0.0.5.dist-info/RECORD
