Metadata-Version: 2.1
Name: middleware2mysql
Version: 0.0.5
Summary: use kafka and redis by mysql
Home-page: https://github.com/hanhang-han/mysqlplus_pkg
Author: hanhang
Author-email: hanhang@360.com
Requires-Dist: aiomultiprocess >=0.9.0
Requires-Dist: async-timeout
Requires-Dist: dill >=0.3.8
Requires-Dist: greenlet >=3.0.3
Requires-Dist: multiprocess >=0.70.16
Requires-Dist: mysql ==0.0.3
Requires-Dist: mysql-connector-python >=8.3.0
Requires-Dist: mysqlclient >=2.2.4
Requires-Dist: PyMySQL >=1.1.0
Requires-Dist: SQLAlchemy >=2.0.28
Requires-Dist: typing-extensions >=4.10.0
